README.md
setup.py
eic_db_request.egg-info/PKG-INFO
eic_db_request.egg-info/SOURCES.txt
eic_db_request.egg-info/dependency_links.txt
eic_db_request.egg-info/requires.txt
eic_db_request.egg-info/top_level.txt
eic_db_request/config/__init__.py
eic_db_request/config/config_eic.py
eic_db_request/query/__init__.py
eic_db_request/query/_utils.py
eic_db_request/query/events.py
eic_db_request/query/files.py
eic_db_request/query/hk.py
eic_db_request/query/report.py
eic_db_request/query/shifts.py
eic_db_request/query_builder/__init__.py
eic_db_request/query_builder/attitude_file.py
eic_db_request/query_builder/calibration.py
eic_db_request/query_builder/events.py
eic_db_request/query_builder/hk.py
eic_db_request/query_builder/orbito_file.py
eic_db_request/query_builder/query.py
eic_db_request/query_builder/query_builder.py
eic_db_request/query_builder/reports.py
eic_db_request/query_builder/shift.py